README.rst
kafka_replayer.py
setup.py
kafka_replayer.egg-info/PKG-INFO
kafka_replayer.egg-info/SOURCES.txt
kafka_replayer.egg-info/dependency_links.txt
kafka_replayer.egg-info/not-zip-safe
kafka_replayer.egg-info/requires.txt
kafka_replayer.egg-info/top_level.txt
test/__init__.py
test/test_kafka_replayer.py