Metadata-Version: 1.1
Name: kafka-replayer
Version: 1.0.1
Summary: Timestamp-based Kafka topic replayer
Home-page: https://github.com/SiftScience/python-kafka-replayer
Author: Sift Science
Author-email: opensource@siftscience.com
License: Apache License 2.0
Keywords: kafka consumer replayer replay
Platform: UNKNOWN
Classifier: Development Status :: 5 - Production/Stable
Classifier: Intended Audience :: Developers
Classifier: Topic :: System :: Distributed Computing
Classifier: Topic :: System :: Clustering
Classifier: License :: OSI Approved :: Apache Software License
Classifier: Programming Language :: Python :: 2.7
Classifier: Programming Language :: Python :: 3.4
Classifier: Programming Language :: Python :: 3.5
